claude_traces_client/__init__.py
claude_traces_client/paths.py
claude_traces_client/uploader.py
claude_traces_client/wrapper.py
claude_traces_client-0.1.2.dist-info/METADATA
claude_traces_client-0.1.2.dist-info/WHEEL
claude_traces_client-0.1.2.dist-info/RECORD
