Metadata-Version: 2.4
Name: claude-traces-client
Version: 0.1.2
Summary: Extract and upload Claude Code traces
Project-URL: Homepage, https://github.com/rhuang/claude-traces-client
License-Expression: MIT
Classifier: License :: OSI Approved :: MIT License
Classifier: Operating System :: OS Independent
Classifier: Programming Language :: Python :: 3
Classifier: Programming Language :: Python :: 3.10
Classifier: Programming Language :: Python :: 3.11
Classifier: Programming Language :: Python :: 3.12
Requires-Python: >=3.10
Requires-Dist: claude-code-sdk>=0.0.25
Requires-Dist: httpx>=0.25.0
